salto/__init__.py
salto/axis.py
tests/__init__.py
tests/test_axis.py
salto-0.0.4.dist-info/LICENSE
salto-0.0.4.dist-info/METADATA
salto-0.0.4.dist-info/WHEEL
salto-0.0.4.dist-info/top_level.txt
salto-0.0.4.dist-info/RECORD
