Metadata-Version: 2.1
Name: salto
Version: 0.0.4
Summary: Playing with embedding vectors
Home-page: https://github.com/krzjoa/salto
Author: Krzysztof Joachimiak
Author-email: Krzysztof Joachimiak <joachimiak.krzysztof@gmail.com>
Project-URL: Homepage, https://github.com/krzjoa/salto
Project-URL: Bug Tracker, https://github.com/krzjoa/salto/issues
Classifier: Programming Language :: Python :: 3
Classifier: License :: OSI Approved :: MIT License
Classifier: Operating System :: OS Independent
Requires-Python: >=3.7
License-File: LICENSE
